{
  "current_page": 1,
  "data": [
    {
      "id": 35,
      "nama": "Yuliari Peter Batubara",
      "ttl": "tes",
      "agama": "Islam",
      "email": "test@gmail.com",
      "jabatan": "Wabendum Program",
      "photo": "uploads/image/pengurus/Juliari-Peter-Batubara_160110035548.jpg",
      "biografi": "<p>das</p>",
      "created_at": "2020-09-12 08:17:00",
      "updated_at": "2020-10-11 00:00:00"
    },
    {
      "id": 34,
      "nama": "Rudiyanto Chen",
      "ttl": null,
      "agama": "",
      "email": null,
      "jabatan": "Wabendum Internal",
      "photo": "uploads/image/pengurus/rudi-_160110035447.jpg",
      "biografi": "",
      "created_at": "2020-09-12 08:17:00",
      "updated_at": "2020-09-12 08:17:00"
    },
    {
      "id": 33,
      "nama": "Olly Dondo Kambey",
      "ttl": null,
      "agama": "",
      "email": null,
      "jabatan": "Bendahara Umum",
      "photo": "uploads/image/pengurus/olly_160110040111.jpg",
      "biografi": "",
      "created_at": "2020-09-12 08:17:00",
      "updated_at": "2020-09-12 08:17:00"
    },
    {
      "id": 32,
      "nama": "Arief Wibowo",
      "ttl": null,
      "agama": "",
      "email": null,
      "jabatan": "Wasekjen BIdang Pemerintahan",
      "photo": "uploads/image/pengurus/ariefdpp_190930122304.jpg",
      "biografi": "",
      "created_at": "2020-09-12 08:17:00",
      "updated_at": "2020-09-12 08:17:00"
    },
    {
      "id": 31,
      "nama": "Sadarestuwati",
      "ttl": null,
      "agama": "",
      "email": null,
      "jabatan": "Wasekjen BIdang Kerakyatan",
      "photo": "uploads/image/pengurus/sadaretu_190930122524.jpg",
      "biografi": "",
      "created_at": "2020-09-12 08:17:00",
      "updated_at": "2020-09-12 08:17:00"
    },
    {
      "id": 30,
      "nama": "Utut Adianto",
      "ttl": null,
      "agama": "",
      "email": null,
      "jabatan": "Wasekjen Bidang Internal",
      "photo": "uploads/image/pengurus/utut_160110035846.jpg",
      "biografi": "",
      "created_at": "2020-09-12 08:17:00",
      "updated_at": "2020-09-12 08:17:00"
    },
    {
      "id": 29,
      "nama": "Hasto Kristiyanto",
      "ttl": "Yoqyakarta, 7 Juli 1966",
      "agama": "Kristen Katolik",
      "email": "Hasto@pdiperjuangan.id",
      "jabatan": "Sekretaris Jenderal",
      "photo": "uploads/image/pengurus/hasto_160110034751.jpg",
      "biografi": "<p>Ir. Hasto Kristiyanto, MM. (lahir di Yoqyakarta, 7 Juli 1966; umur 54 tahun) adalah politikus berkebangsaan lndonesia . Saat ini menjabat sebagai Sekretaris Jenderal Partai Demokrasi lndonesia Periuangan, menggantikan Tjahjo Kumolo yang diangkat sebagai Menteri Dalam Negeri. Sebelumnya, Hasto menjabat Wakil Sekretaris Jenderal PDIP merangkap sebagai salah satu deputi Tim Transisi menjelang pelantikan Joko Widodo sebagai Presiden ke-7 Republik lndonesia, 20 Oktober 2014. Pernah pula menjadi anggota DPR RI periode 2004-2009 dari fraksi PDIP Saat itu, dia duduk di Komisi VI yang menangani permasalahan perdagangan, perindustrian, investasi dan koperasi.</p><h4><strong>Kehidupan Pribadi</strong></h4><p>Hasto Kristiyanto lahir di Yogyakarta pada tanggal 7 Juli 1966. Sejak duduk di bangku SMA, dia sudah tertarik dengan dunia politik. Selama bersekolah di SMA Kolese de Britto Yogyakarta, dia gemar membaca buku politik. Kemudian melanjutkan studinya di Fakultas Teknik Universitas Gadjah Mada (UGM) Yogyakarta, lulus tahun 1991 dengan gelar Insinyur.</p><p>Selama masih berstatus mahasiswa, Hasto aktif mengikuti kegiatan organisasi. Dia bahkan sempat menjabat sebagai Ketua Senat &nbsp;Mahasiswa Fakultas Teknik UGM. Dari sinilah, Hasto semakin mantap terjun ke kancah politik. Hasto mengakui, niatnya yang bulat untuk terjun ke dunia politik tak lepas dari campur tangan gereja. Baginya, Kehidupan gereja sangat berperan atas pembentukan dirinya melalui kaderisasi dan bimbingan seorang pastor. Bahkan, hingga kini, Hasto masih melakukan bimbingan rohani dengan Pastor Herman Joseph Suhardiyanto SJ.</p><p>Hasto kemudian memutuskan untuk menjadi anggota Partai Demokrasi Indonesia Perjuangan Bersama partai inilah, dia terpilih menjadi anggota DPR RI untuk periode 2004-2009 dari daerah pemilihan Ngawi, Magetan, Ponorogo, Pacitan, dan Trenggalek, Jawa Timur (yang sebagian merupakan eks Keresidenan Madiun (Plat AE)).</p><p>Sewaktu menjadi anggota DPR, Hasto menolak beberapa RUU dii antaranya RUU free Trade Zone Kawasan Batam. Di balik RUU itu, menurutnya, terdapat kepentingan perusahaan-perusahaan besar yang ingin berinvestasi di wilayah itu. Namun, RUU tetap diproses hingga &nbsp;menjadi Undang- Undang.</p><p>Semasa kekosongan sebagai anggota DPR, ia &nbsp;menjadi pengajar dan motivator di internal partai. Dalam seminggu, ia menghabiskan lima hari untuk partai, sehari untuk keluarga, dan sisanya bersama rekan-rekannya.</p><h4>Pendidikan</h4><ul><li>SD Gentan Yogya (1972-1979)</li><li>SMP Negeri Gentan Yogya (1979-1982)</li><li>SMA Kolese De Britto Yogyakarta (1982-1985)</li><li>Fakultas Teknik UGM Yogyakarta (1985-1991)</li><li>Prasetya Mulya Business School, Jakarta, (1997-2000)</li></ul><h4>Karier</h4><ul><li>Project Manager Departemen Marketing PT Rekayasa lndustri (1992\u20142002)</li><li>Project Director PT Prada Nusa Perkasa (2003-sekarang)</li></ul><p>&nbsp;</p>",
      "created_at": "2020-09-12 08:17:00",
      "updated_at": "2020-09-28 00:00:00"
    },
    {
      "id": 28,
      "nama": "Prananda Prabowo",
      "ttl": null,
      "agama": "",
      "email": null,
      "jabatan": "Ekonomi Kreatif & Ekonomi Digital",
      "photo": "uploads/image/pengurus/prananda_160109091547.jpg",
      "biografi": "",
      "created_at": "2020-09-12 08:17:00",
      "updated_at": "2020-09-12 08:17:00"
    },
    {
      "id": 27,
      "nama": "Hamka Haq",
      "ttl": null,
      "agama": "",
      "email": null,
      "jabatan": "Keagamaan dan Kepercayaan",
      "photo": "uploads/image/pengurus/hamka_160110031446.jpg",
      "biografi": "",
      "created_at": "2020-09-12 08:17:00",
      "updated_at": "2020-09-12 08:17:00"
    },
    {
      "id": 26,
      "nama": "Eriko Sotarduga",
      "ttl": null,
      "agama": "",
      "email": null,
      "jabatan": "Pemuda dan Olahraga",
      "photo": "uploads/image/pengurus/eriko dpp_190930121537.jpg",
      "biografi": "",
      "created_at": "2020-09-12 08:17:00",
      "updated_at": "2020-09-12 08:17:00"
    },
    {
      "id": 25,
      "nama": "Wiranti Sukamdani",
      "ttl": null,
      "agama": "",
      "email": null,
      "jabatan": "Pariwisata",
      "photo": "uploads/image/pengurus/wiranti_160110023548.jpg",
      "biografi": "",
      "created_at": "2020-09-12 08:17:00",
      "updated_at": "2020-09-12 08:17:00"
    },
    {
      "id": 24,
      "nama": "Nusirwan Sujono",
      "ttl": null,
      "agama": "",
      "email": null,
      "jabatan": "Industri, Ketenagakerjaan & Jamsos",
      "photo": "uploads/image/pengurus/Nusirwan-Sujono_160110023239.jpg",
      "biografi": "",
      "created_at": "2020-09-12 08:17:00",
      "updated_at": "2020-09-12 08:17:00"
    },
    {
      "id": 23,
      "nama": "Tri Rismaharini",
      "ttl": null,
      "agama": "",
      "email": null,
      "jabatan": " Kebudayaan",
      "photo": "uploads/image/pengurus/risma dpp_190930121409.jpg",
      "biografi": "",
      "created_at": "2020-09-12 08:17:00",
      "updated_at": "2020-09-12 08:17:00"
    },
    {
      "id": 22,
      "nama": "Sri Rahayu",
      "ttl": null,
      "agama": "",
      "email": null,
      "jabatan": "Kesehatan dan Anak",
      "photo": "uploads/image/pengurus/sri-rahayu_160110023333.jpg",
      "biografi": "",
      "created_at": "2020-09-12 08:17:00",
      "updated_at": "2020-09-12 08:17:00"
    },
    {
      "id": 21,
      "nama": "Mindo Sianipar",
      "ttl": null,
      "agama": "",
      "email": null,
      "jabatan": "Koperasi  & Kesejahteraan Rakyat",
      "photo": "uploads/image/pengurus/mindo_160110040037.jpg",
      "biografi": "",
      "created_at": "2020-09-12 08:17:00",
      "updated_at": "2020-09-12 08:17:00"
    },
    {
      "id": 20,
      "nama": "Ribka Tjiptaning",
      "ttl": null,
      "agama": "",
      "email": null,
      "jabatan": "Penanggulangan Bencana",
      "photo": "uploads/image/pengurus/tibka_t_160110033010.jpg",
      "biografi": "",
      "created_at": "2020-09-12 08:17:00",
      "updated_at": "2020-09-12 08:17:00"
    },
    {
      "id": 19,
      "nama": "Ahmad Basarah",
      "ttl": null,
      "agama": "",
      "email": null,
      "jabatan": "Luar Negeri:",
      "photo": "uploads/image/pengurus/basarah dpp_190930121929.jpg",
      "biografi": "",
      "created_at": "2020-09-12 08:17:00",
      "updated_at": "2020-09-12 08:17:00"
    },
    {
      "id": 18,
      "nama": "Rohmin Dahuri.",
      "ttl": null,
      "agama": "",
      "email": null,
      "jabatan": "Kelautan, Perikanan dan Nelayan:",
      "photo": "uploads/image/pengurus/rohmin_160110022753.jpg",
      "biografi": "",
      "created_at": "2020-09-12 08:17:00",
      "updated_at": "2020-09-12 08:17:00"
    },
    {
      "id": 17,
      "nama": "I Made Urip",
      "ttl": null,
      "agama": "",
      "email": null,
      "jabatan": "Kehutanan dan Lingkungan Hidup",
      "photo": "uploads/image/pengurus/made urip_190930120526.jpg",
      "biografi": "",
      "created_at": "2020-09-12 08:17:00",
      "updated_at": "2020-09-12 08:17:00"
    },
    {
      "id": 16,
      "nama": " Said Abdullah",
      "ttl": null,
      "agama": "",
      "email": null,
      "jabatan": "Bidang Perekonomian",
      "photo": "uploads/image/pengurus/said  2_190930120352.jpg",
      "biografi": "",
      "created_at": "2020-09-12 08:17:00",
      "updated_at": "2020-09-12 08:17:00"
    },
    {
      "id": 15,
      "nama": "Yasonna H. Laoly",
      "ttl": null,
      "agama": "",
      "email": null,
      "jabatan": "Hukum HAM & Perundangan",
      "photo": "uploads/image/pengurus/ys_190930120114.jpg",
      "biografi": "",
      "created_at": "2020-09-12 08:17:00",
      "updated_at": "2020-09-12 08:17:00"
    },
    {
      "id": 14,
      "nama": "Puan Maharani",
      "ttl": null,
      "agama": "",
      "email": null,
      "jabatan": "Politik dan Keamanan",
      "photo": "uploads/image/pengurus/puan_160109084124.jpg",
      "biografi": "",
      "created_at": "2020-09-12 08:17:00",
      "updated_at": "2020-09-12 08:17:00"
    },
    {
      "id": 11,
      "nama": "Sukur Nababan",
      "ttl": null,
      "agama": "",
      "email": null,
      "jabatan": "Keanggotaan dan Organisasi",
      "photo": "uploads/image/pengurus/sukur_190929115403.jpg",
      "biografi": "",
      "created_at": "2020-09-12 08:17:00",
      "updated_at": "2020-09-12 08:17:00"
    },
    {
      "id": 10,
      "nama": "Djarot S. Hidayat",
      "ttl": null,
      "agama": "",
      "email": null,
      "jabatan": "Ideologi dan Kaderisasi",
      "photo": "uploads/image/pengurus/djarot dpp_190929115304.jpg",
      "biografi": "",
      "created_at": "2020-09-12 08:17:00",
      "updated_at": "2020-09-12 08:17:00"
    },
    {
      "id": 9,
      "nama": "Bambang Wuryanto",
      "ttl": null,
      "agama": "",
      "email": null,
      "jabatan": "Pemenangan Pemilu",
      "photo": "uploads/image/pengurus/pacul2_190929115044.jpg",
      "biografi": "",
      "created_at": "2020-09-12 08:17:00",
      "updated_at": "2020-09-12 08:17:00"
    },
    {
      "id": 8,
      "nama": "Komarudin Watubun",
      "ttl": null,
      "agama": "",
      "email": null,
      "jabatan": "Ketua Bidang Kehormatan Partai",
      "photo": "uploads/image/pengurus/Komarudin_160109080714.jpg",
      "biografi": "",
      "created_at": "2020-09-12 08:17:00",
      "updated_at": "2020-09-12 08:17:00"
    },
    {
      "id": 7,
      "nama": "Megawati Soekarnoputri",
      "ttl": null,
      "agama": "",
      "email": null,
      "jabatan": "Ketua Umum",
      "photo": "uploads/image/pengurus/Ibu-mega_160108102153.jpg",
      "biografi": "",
      "created_at": "2020-09-12 08:17:00",
      "updated_at": "2020-09-12 08:17:00"
    }
  ],
  "first_page_url": "http://data.pdiperjuangan.id/api/partai/pengurus/data?page=1",
  "from": 1,
  "last_page": 1,
  "last_page_url": "http://data.pdiperjuangan.id/api/partai/pengurus/data?page=1",
  "next_page_url": null,
  "path": "http://data.pdiperjuangan.id/api/partai/pengurus/data",
  "per_page": 100,
  "prev_page_url": null,
  "to": 27,
  "total": 27
}
